maplocal/__about__.py
maplocal/__init__.py
maplocal/_version.py
maplocal/env.py
maplocal/maplocal.py
maplocal/maplocal_wsl.py
maplocal-0.2.1.dist-info/METADATA
maplocal-0.2.1.dist-info/WHEEL
maplocal-0.2.1.dist-info/licenses/LICENSE.txt
maplocal-0.2.1.dist-info/RECORD
