Metadata-Version: 2.1
Name: maplocal
Version: 0.2.1
Project-URL: Documentation, https://github.com/unknown/maplocal#readme
Project-URL: Issues, https://github.com/unknown/maplocal/issues
Project-URL: Source, https://github.com/unknown/maplocal
Author-email: John <J.gunstone@maxfordham.com>
License-Expression: 0BSD
License-File: LICENSE.txt
Classifier: Development Status :: 4 - Beta
Classifier: Programming Language :: Python
Classifier: Programming Language :: Python :: 3.7
Classifier: Programming Language :: Python :: 3.8
Classifier: Programming Language :: Python :: 3.9
Classifier: Programming Language :: Python :: 3.10
Classifier: Programming Language :: Python :: 3.11
Classifier: Programming Language :: Python :: Implementation :: CPython
Classifier: Programming Language :: Python :: Implementation :: PyPy
Requires-Python: >=3.7
Requires-Dist: pydantic-settings
Requires-Dist: pydantic>2
